capsnet/__init__.py
capsnet/layers.py
capsnet/losses.py
capsnet/models.py
capsnet/setup.py
capsnet/utils.py
datasets/__init__.py
datasets/setup.py
datasets/ucf101.py
datasets/ucf50.py
datasets/utils.py
hexcapsnet-0.0.7a0.dist-info/METADATA
hexcapsnet-0.0.7a0.dist-info/WHEEL
hexcapsnet-0.0.7a0.dist-info/top_level.txt
hexcapsnet-0.0.7a0.dist-info/RECORD
