Metadata-Version: 2.1
Name: hexcapsnet
Version: 0.0.7a0
Summary: Libs capsnets
Home-page: UNKNOWN
Author: Vladislav Ovchinnikov
Author-email: vladovchinnikov950@gmail.com
License: MIT
Keywords: capsnet ai classification
Platform: UNKNOWN
Classifier: Development Status :: 3 - Alpha
Classifier: License :: OSI Approved :: MIT License
Classifier: Programming Language :: Python :: 3.6
Requires-Dist: tensorflow (==2.4.1)
Requires-Dist: keras
Requires-Dist: tf-slim
